pykeypass/__init__.py
pykeypass-2024.4.19.dist-info/METADATA
pykeypass-2024.4.19.dist-info/WHEEL
pykeypass-2024.4.19.dist-info/entry_points.txt
pykeypass-2024.4.19.dist-info/top_level.txt
pykeypass-2024.4.19.dist-info/RECORD
