Metadata-Version: 2.1
Name: pykeypass
Version: 2024.4.19
Author-email: bh <bhammond@waubonsee.edu>
Project-URL: Homepage, https://github.com/darrida/pykeypass
Requires-Python: <3.13,>=3.9
Requires-Dist: pykeepass ==4.0.7.post1
Requires-Dist: lxml ==5.2.1
Requires-Dist: click ==8.1.7
Requires-Dist: setuptools ==69.5.1
Requires-Dist: python-version <3
Provides-Extra: test
Requires-Dist: pytest ; extra == 'test'
Requires-Dist: pytest-asyncio ; extra == 'test'
Requires-Dist: pytest-mock ; extra == 'test'
